tic_tac_toe_miked/__init__.py
tic_tac_toe_miked/classes.py
tic_tac_toe_miked/ttt.py
tic_tac_toe_miked-0.4.dist-info/METADATA
tic_tac_toe_miked-0.4.dist-info/WHEEL
tic_tac_toe_miked-0.4.dist-info/licenses/LICENSE
tic_tac_toe_miked-0.4.dist-info/RECORD
