Metadata-Version: 2.1
Name: tic_tac_toe_miked
Version: 0.4
Summary: Tic-Tac-Toe console game with AI
Project-URL: Homepage, https://github.com/mike0618/Portfolio_Projects/tree/2_Tic_Tac_Toe/PKG
Project-URL: Bug Tracker, https://github.com/mike0618/Portfolio_Projects/issues
Author-email: "miked (Mike Zubko)" <mike0618dev@yahoo.com>
License: Copyright (c) 2018 The Python Packaging Authority
Classifier: License :: OSI Approved :: MIT License
Classifier: Operating System :: OS Independent
Classifier: Programming Language :: Python :: 3
Requires-Python: >=3.7
